flask_xxl/__init__.py
flask_xxl/basemodels.py
flask_xxl/baseviews.py
flask_xxl/basewidgets.py
flask_xxl/cli.py
flask_xxl/filters.py
flask_xxl/hooks.py
flask_xxl/main.py
flask_xxl/manage.py
flask_xxl/mr_bob.py
flask_xxl/testing.py
flask_xxl/templates/blueprint/.mrbob.ini
flask_xxl/templates/blueprint/__init__.py
flask_xxl/templates/blueprint/+blueprint.name+/__init__.py.bob
flask_xxl/templates/blueprint/+blueprint.name+/context_processors.py.bob
flask_xxl/templates/blueprint/+blueprint.name+/filters.py.bob
flask_xxl/templates/blueprint/+blueprint.name+/forms.py.bob
flask_xxl/templates/blueprint/+blueprint.name+/models.py.bob
flask_xxl/templates/blueprint/+blueprint.name+/urls.py.bob
flask_xxl/templates/blueprint/+blueprint.name+/views.py.bob
flask_xxl/templates/project/.mrbob.ini
flask_xxl/templates/project/__init__.py
flask_xxl/templates/project/+project.name+/__init__.py
flask_xxl/templates/project/+project.name+/app.py.bob
flask_xxl/templates/project/+project.name+/ext.py.bob
flask_xxl/templates/project/+project.name+/imports.py.bob
flask_xxl/templates/project/+project.name+/local_settings.py.bob
flask_xxl/templates/project/+project.name+/manage.py.bob
flask_xxl/templates/project/+project.name+/settings.py.bob
flask_xxl/templates/project/+project.name+/+project.name+/__init__.py.bob
flask_xxl/templates/project/+project.name+/+project.name+/context_processors.py.bob
flask_xxl/templates/project/+project.name+/+project.name+/models.py.bob
flask_xxl/templates/project/+project.name+/+project.name+/urls.py.bob
flask_xxl/templates/project/+project.name+/+project.name+/views.py.bob
flask_xxl-0.9.14.dist-info/DESCRIPTION.rst
flask_xxl-0.9.14.dist-info/METADATA
flask_xxl-0.9.14.dist-info/RECORD
flask_xxl-0.9.14.dist-info/WHEEL
flask_xxl-0.9.14.dist-info/entry_points.txt
flask_xxl-0.9.14.dist-info/metadata.json
flask_xxl-0.9.14.dist-info/top_level.txt
